<annotation>
	<folder>obj0000</folder>
	<filename>obj0000_frame0000013.jpg</filename>
	<path>/Users/Elliott/Documents/Research/Labeling/Trash/drive-download-20180210T164220Z-001/obj0000/obj0000_frame0000013.jpg</path>
	<source>
		<database>Unknown</database>
	</source>
	<size>
		<width>480</width>
		<height>360</height>
		<depth>3</depth>
	</size>
	<segmented>0</segmented>
	<object>
		<name>plastic</name>
		<pose>Unspecified</pose>
		<truncated>0</truncated>
		<difficult>0</difficult>
		<bndbox>
			<xmin>435</xmin>
			<ymin>261</ymin>
			<xmax>473</xmax>
			<ymax>329</ymax>
		</bndbox>
	</object>
	<object>
		<name>rov</name>
		<pose>Unspecified</pose>
		<truncated>1</truncated>
		<difficult>0</difficult>
		<bndbox>
			<xmin>190</xmin>
			<ymin>38</ymin>
			<xmax>480</xmax>
			<ymax>252</ymax>
		</bndbox>
	</object>
	<object>
		<name>timestamp</name>
		<pose>Unspecified</pose>
		<truncated>1</truncated>
		<difficult>0</difficult>
		<bndbox>
			<xmin>376</xmin>
			<ymin>340</ymin>
			<xmax>478</xmax>
			<ymax>360</ymax>
		</bndbox>
	</object>
	<object>
		<name>timestamp</name>
		<pose>Unspecified</pose>
		<truncated>0</truncated>
		<difficult>0</difficult>
		<bndbox>
			<xmin>42</xmin>
			<ymin>21</ymin>
			<xmax>138</xmax>
			<ymax>64</ymax>
		</bndbox>
	</object>
	<object>
		<name>timestamp</name>
		<pose>Unspecified</pose>
		<truncated>0</truncated>
		<difficult>0</difficult>
		<bndbox>
			<xmin>364</xmin>
			<ymin>25</ymin>
			<xmax>446</xmax>
			<ymax>53</ymax>
		</bndbox>
	</object>
</annotation>
