<annotation>
	<folder>obj0707</folder>
	<filename>obj0707_frame0000020.jpg</filename>
	<path>/home/jungseok/Desktop/image_files/obj0707/obj0707_frame0000020.jpg</path>
	<source>
		<database>Unknown</database>
	</source>
	<size>
		<width>480</width>
		<height>360</height>
		<depth>3</depth>
	</size>
	<segmented>0</segmented>
	<object>
		<name>rubber</name>
		<pose>Unspecified</pose>
		<truncated>0</truncated>
		<difficult>0</difficult>
		<bndbox>
			<xmin>129</xmin>
			<ymin>73</ymin>
			<xmax>264</xmax>
			<ymax>258</ymax>
		</bndbox>
	</object>
	<object>
		<name>metal</name>
		<pose>Unspecified</pose>
		<truncated>0</truncated>
		<difficult>0</difficult>
		<bndbox>
			<xmin>343</xmin>
			<ymin>205</ymin>
			<xmax>448</xmax>
			<ymax>247</ymax>
		</bndbox>
	</object>
	<object>
		<name>plastic</name>
		<pose>Unspecified</pose>
		<truncated>0</truncated>
		<difficult>0</difficult>
		<bndbox>
			<xmin>293</xmin>
			<ymin>214</ymin>
			<xmax>345</xmax>
			<ymax>253</ymax>
		</bndbox>
	</object>
	<object>
		<name>timestamp</name>
		<pose>Unspecified</pose>
		<truncated>0</truncated>
		<difficult>0</difficult>
		<bndbox>
			<xmin>20</xmin>
			<ymin>73</ymin>
			<xmax>450</xmax>
			<ymax>92</ymax>
		</bndbox>
	</object>
	<object>
		<name>timestamp</name>
		<pose>Unspecified</pose>
		<truncated>0</truncated>
		<difficult>0</difficult>
		<bndbox>
			<xmin>22</xmin>
			<ymin>276</ymin>
			<xmax>476</xmax>
			<ymax>315</ymax>
		</bndbox>
	</object>
</annotation>
